dohko/__init__.py
dohko/circuits/__init__.py
dohko/circuits/circuit.py
dohko/commitments/__init__.py
dohko/commitments/kzg/__init__.py
dohko/commitments/kzg/kzg.py
dohko/commitments/kzg/kzg_optimized.py
dohko/commitments/mkzg/ecc/__init__.py
dohko/commitments/mkzg/mkzg.py
dohko/commitments/plookup/Introduction.md
dohko/commitments/plookup/README.md
dohko/commitments/plookup/__init__.py
dohko/commitments/plookup/benchmark.py
dohko/commitments/plookup/program.py
dohko/commitments/plookup/prover.py
dohko/commitments/plookup/setup.py
dohko/commitments/plookup/transcript.py
dohko/commitments/plookup/verifier.py
dohko/ops/__init__.py
dohko/ops/conv.py
dohko/ops/elementwise.py
dohko/ops/from_onnx.py
dohko/ops/gemm.py
dohko/ops/onnx_utils.py
dohko/polynomials/__init__.py
dohko/polynomials/poly.py
dohko/prover/__init__.py
dohko/prover/prover.py
dohko/transcript/__init__.py
dohko/transcript/merlin/__init__.py
dohko/transcript/merlin/keccak.py
dohko/transcript/merlin/merlin_transcript.py
dohko/transcript/merlin/strobe.py
dohko/transcript/transcript.py
dohko/types/__init__.py
dohko/types/gate.py
dohko/types/proof.py
dohko/utils/__init__.py
dohko/utils/curve.py
dohko/utils/curve_optimized.py
dohko/utils/kzg.py
dohko/utils/kzg_optimized.py
dohko/utils/kzg_test.py
dohko/utils/poly.py
dohko/utils/poly_optimized.py
dohko/utils/transcript.py
dohko/utils/transcript_optimized.py
dohko/utils/util.py
dohko/utils/utils.py
dohko/verifier/__init__.py
dohko/verifier/verifier.py
dohko/zkgrad/.gitignore
dohko/zkgrad/README.md
dohko/zkgrad/poetry.lock
dohko/zkgrad/pyproject.toml
dohko/zkgrad/tests/assets/.gitkeep
dohko/zkgrad/tests/test_comp.py
dohko/zkgrad/tests/test_core_math.py
dohko/zkgrad/tests/test_graph.py
dohko/zkgrad/tests/test_hyp.py
dohko/zkgrad/tests/test_neuron.py
dohko/zkgrad/tests/test_trig.py
dohko/zkgrad/tests/utils.py
dohko/zkgrad/zkgrad/__init__.py
dohko/zkgrad/zkgrad/arithmetics/__init__.py
dohko/zkgrad/zkgrad/arithmetics/base.py
dohko/zkgrad/zkgrad/arithmetics/comp.py
dohko-0.1.0.dist-info/LICENSE
dohko-0.1.0.dist-info/METADATA
dohko-0.1.0.dist-info/WHEEL
dohko-0.1.0.dist-info/RECORD
