Metadata-Version: 2.1
Name: dohko
Version: 0.1.0
Summary: zkGraph proving backend
License: MIT
Author: AE Studio
Requires-Python: >3.11.0,<4.0
Classifier: License :: OSI Approved :: MIT License
Classifier: Programming Language :: Python :: 3
Classifier: Programming Language :: Python :: 3.12
Requires-Dist: dill (>=0.3.8,<0.4.0)
Requires-Dist: onnx (>=1.16.1,<2.0.0)
Requires-Dist: onnxruntime (>=1.18.1,<2.0.0)
Requires-Dist: py-ecc (>=7.0.1,<8.0.0)
Requires-Dist: pybind11 (>=2.13.1,<3.0.0)
Requires-Dist: pydantic (>=2.8.0,<3.0.0)
Requires-Dist: scikit-learn (>=1.5.1,<2.0.0)
Requires-Dist: sympy (>=1.12.1,<2.0.0)
Requires-Dist: torch (==2.2.0)
